flow_panel/__init__.py
flow_panel/flow_panel.py
flow_panel-0.0.3.dist-info/METADATA
flow_panel-0.0.3.dist-info/WHEEL
flow_panel-0.0.3.dist-info/top_level.txt
flow_panel-0.0.3.dist-info/RECORD
