Metadata-Version: 2.1
Name: flow_panel
Version: 0.0.3
Home-page: https://github.com/bin2ai/flow-panel
Classifier: Programming Language :: Python :: 3
Classifier: License :: OSI Approved :: MIT License
Classifier: Operating System :: OS Independent
